Workbook

Sheet Cover
A1: Wise PLC (WISE.L) — DCF Valuation Model
A3: Prepared by | B3: Parth Kabrawala
A4: Date | B4: 46174
A5: Disclaimer: For educational purposes only. Not investment advice.
A6: Key output summary: Implied share price (perpetuity), implied share price (exit multiple), current share price, upside/downside
A8: Methodology
A9: 5-Year DCF using two-stage valuation:
A10: Stage 1: Explicit FCFF forecast period
A11: Stage 2: Terminal Value via (a) Gordon Growth perpetuity (b) EV/EBITDA Exit multiple
A12: WACC: 8.47%
A14: Key outputs:
A15: Implied Share Price (perpetuity method) | B15: =DCF!B19 -> 16.779112
A16: Current Market Price | B16: 10.87
A17: Implied (Upside)/(Downside) | B17: =DCF!B21 -> 0.54361656

Sheet Assumptions
A1: ASSUMPTIONS
B2: FY2023A | C2: FY2024A | D2: FY2025A | E2: FY2026E | F2: FY2027E | G2: FY2028E | H2: FY2029E | I2: FY2030E
A3: Total Income Growth % | B3: 0 | C3: 0.46473761 | D3: 0.16476669 | E3: 0.18 | F3: 0.16 | G3: 0.14 | H3: 0.12 | I3: 0.1
A4: Gross Margin % | B4: 0.66189587 | C4: 0.77349005 | D4: 0.7950152
A5: Operating Margin % | B5: 0.16303671 | C5: 0.35537775 | D5: 0.35234043 | E5: 0.33 | F5: 0.34 | G5: 0.35 | H5: 0.36 | I5: 0.37
A6: Net Margin % | B6: 0.11823273 | C6: 0.2510798 | D6: 0.25331307
A7: Effective Tax Rate % | B7: -0.0337067 | C7: -0.089782624 | D7: -0.090030395 | E7: 0.26 | F7: 0.26 | G7: 0.26 | H7: 0.26 | I7: 0.26
A8: WACC & VALUATION INPUTS
A9: Risk Free Rate (10Y UK Gilt) | B9: 0.042
A10: Equity Risk Premium | B10: 0.055
A11: Beta | B11: 0.9
A12: Cost of Equity | B12: =B9+(B11*B10) -> 0.0915
A13: Cost of Debt (pre-tax) | B13: 0.045
A14: Tax Rate | B14: 0.26
A15: Debt / (Debt + Equity) | B15: =BS!E21/(BS!E21+BS!E39) -> 0.14532339
A16: WACC | B16: =Sensitivity!B16 -> 0.084742463 | C16: =(B15*B13)+((1-B15)*B12) -> 0.084742463
A17: Terminal Growth Rate | B17: =Sensitivity!B17 -> 0.03
A18: Exit Multiple (EV/EBITDA) | B18: =Sensitivity!J17 -> 0

Sheet IS
B1: FY2023A | C1: FY2024A | D1: FY2025A | E1: FY2026E | F1: FY2027E | G1: FY2028E | H1: FY2029E | I1: FY2030E
A2: Total Income | B2: 964.2 | C2: 1412.3 | D2: 1645 | E2: =D2*(1+Assumptions!E3) -> 1941.1 | F2: =E2*(1+Assumptions!F3) -> 2251.676 | G2: =F2*(1+Assumptions!G3) -> 2566.9106 | H2: =G2*(1+Assumptions!H3) -> 2874.9399 | I2: =H2*(1+Assumptions!I3) -> 3162.4339
A3: Cost of Sales | B3: -308.2 | C3: -307.4 | D3: -328.1
A4: Net Credit Losses | B4: -17.8 | C4: -12.5 | D4: -9.1
A5: Gross Profit | B5: 638.2 | C5: 1092.4 | D5: 1307.8
A6: Admin Expenses | B6: -494.5 | C6: -615.9 | D6: -768.6
A7: Operating Profit | B7: 157.2 | C7: 501.9 | D7: 579.6 | E7: =E2*Assumptions!E5 -> 640.563 | F7: =F2*Assumptions!F5 -> 765.56984 | G7: =G2*Assumptions!G5 -> 898.41872 | H7: =H2*Assumptions!H5 -> 1034.9784 | I7: =I2*Assumptions!I5 -> 1170.1005
A8: Finance Income/Exp | B8: -10.7 | C8: -20.5 | D8: -14.8 | I8: =I3*Assumptions!I6 -> 0
A9: PBT | B9: 146.5 | C9: 481.4 | D9: 564.8 | E9: =E7 -> 640.563 | F9: =F7 -> 765.56984 | G9: =G7 -> 898.41872 | H9: =H7 -> 1034.9784 | I9: =I7 -> 1170.1005
A10: Tax | B10: -32.5 | C10: -126.8 | D10: -148.1 | E10: =E9*Assumptions!$B$14 -> 166.54638 | F10: =F9*Assumptions!$B$14 -> 199.04816 | G10: =G9*Assumptions!$B$14 -> 233.58887 | H10: =H9*Assumptions!$B$14 -> 269.09438 | I10: =I9*Assumptions!$B$14 -> 304.22614
A11: Net Profit | B11: 114 | C11: 354.6 | D11: 416.7 | E11: =E9-E10 -> 474.01662 | F11: =F9-F10 -> 566.52168 | G11: =G9-G10 -> 664.82986 | H11: =H9-H10 -> 765.88399 | I11: =I9-I10 -> 865.8744
A14: Total Income Growth % | B14: =-B14 -> 0 | C14: =(C2-B2)/B2 -> 0.46473761 | D14: =(D2-C2)/C2 -> 0.16476669
A15: Gross Margin % | B15: =B5/B2 -> 0.66189587 | C15: =C5/C2 -> 0.77349005 | D15: =D5/D2 -> 0.7950152
A16: Operating Margin % | B16: =B7/B2 -> 0.16303671 | C16: =C7/C2 -> 0.35537775 | D16: =D7/D2 -> 0.35234043
A17: Net Margin % | B17: =B11/B2 -> 0.11823273 | C17: =C11/C2 -> 0.2510798 | D17: =D11/D2 -> 0.25331307
A18: Effective Tax Rate % | B18: =B10/B2 -> -0.0337067 | C18: =C10/C2 -> -0.089782624 | D18: =D10/D2 -> -0.090030395

Sheet BS
B1: Note | C1: 2023 | D1: 2024 | E1: 2025
A2: Non-current assets Deferred tax assets | B2: 10 | C2: 113.2 | D2: 103 | E2: 84.7
A3: Property, plant and equipment | B3: 12 | C3: 21.1 | D3: 34.3 | E3: 115.9
A4: Intangible assets | B4: 13 | C4: 11.4 | D4: 6.5 | E4: 4
A5: Trade and other receivables | B5: 14 | C5: 17.9 | D5: 32.1 | E5: 38.8
A6: Total non-current assets | C6: 163.6 | D6: 175.9 | E6: 243.4
A7: Current assets
A8: Current tax assets | C8: 6.7 | D8: 4 | E8: 15
A9: Trade and other receivables | B9: 14 | C9: 250 | D9: 442.8 | E9: 347.6
A10: Short-term financial investments | B10: 19 | C10: 3804.5 | D10: 4033.9 | E10: 4654.9
A11: Derivative financial assets | B11: 19 | C11: – | D11: 1.6 | E11: 2.5
A12: Cash and cash equivalents | B12: 15 | C12: 7679.4 | D12: 10479.2 | E12: 13982.8
A13: Total current assets | C13: 11740.6 | D13: 14961.5 | E13: 19002.8
A14: Total assets | C14: 11904.2 | D14: 15137.4 | E14: 19246.2
A15: Non-current liabilities | B15: 16
A16: Trade and other payables | C16: 29.7 | D16: 46.1 | E16: 45.8
A17: Borrowings | B17: 17 | C17: 7.8 | D17: 198.4 | E17: 98.1
A18: Lease liabilities | B18: 18 | D18: 14.8 | E18: 75.9 | I18: Change in NWC | J18: =C13-C29 -> 454.6 | K18: =D13-D29 -> 1072 | L18: =E13-E29 -> 1378.5
A19: Deferred tax liabilities | B19: 10 | C19: 1.1 | D19: 2.4 | E19: 4 | K19: =K18-J18 -> 617.4 | L19: =L18-K18 -> 306.5
A20: Provisions | B20: 20 | C20: 2.7 | D20: 6.3 | E20: 11.9
A21: Total non-current liabilities | C21: 41.3 | D21: 268 | E21: 235.7
A22: Current liabilities | B22: 16
A23: Trade and other payables | C23: 11022.9 | D23: 13861.8 | E23: 17578.8
A24: Borrowings | B24: 17 | C24: 256.6 | D24: 4.3 | E24: 1.3
A25: Lease liabilities | B25: 18 | D25: 6.7 | E25: 10.3
A26: Current tax liabilities | C26: 4 | D26: 6 | E26: 4.4
A27: Derivative financial liabilities | B27: 19 | D27: 1.6 | E27: 3.7
A28: Provisions | B28: 20 | C28: 2.5 | D28: 9.1 | E28: 25.8
A29: Total current liabilities | C29: 11286 | D29: 13889.5 | E29: 17624.3
A30: Total liabilities | C30: 11327.3 | D30: 14157.5 | E30: 17860
A31: Equity
A32: Share capital | B32: 21 | C32: 10.2 | D32: 10.2 | E32: 10.2
A33: Equity merger reserve | C33: -8 | D33: -8 | E33: -8
A34: Share-based payment reserve | C34: 247.4 | D34: 306.5 | E34: 299.4
A35: Own shares reserve | C35: -10.4 | D35: -55.5 | E35: -66.8
A36: Other reserves | C36: -23.3 | D36: -12.4 | E36: -2.1
A37: Currency translation reserve | C37: 3.2 | D37: -3.8 | E37: -14.2
A38: Retained earnings | C38: 357.8 | D38: 742.9 | E38: 1167.7
A39: Total equity | C39: 576.9 | D39: 979.9 | E39: 1386.2
A40: Total liabilities and equity | C40: 11904.2 | D40: 15137.4 | E40: 19246.2

Sheet CF
B1: FY2023A | C1: FY2024A | D1: FY2025A | E1: FY2026E | F1: FY2027E | G1: FY2028E | H1: FY2029E | I1: FY2030E
A2: Operating Profit (EBIT) | B2: =IS!B7 -> 157.2 | C2: =IS!C7 -> 501.9 | D2: =IS!D7 -> 579.6 | E2: =IS!E7 -> 640.563 | F2: =IS!F7 -> 765.56984 | G2: =IS!G7 -> 898.41872 | H2: =IS!H7 -> 1034.9784 | I2: =IS!I7 -> 1170.1005 | L2: Investing Activities | M2: FY2023A | N2: FY2024A | O2: FY2025A
A3: Less: Tax paid | B3: =IS!B10 -> -32.5 | C3: =IS!C10 -> -126.8 | D3: =IS!D10 -> -148.1 | E3: =IS!E10 -> 166.54638 | F3: =IS!F10 -> 199.04816 | G3: =IS!G10 -> 233.58887 | H3: =IS!H10 -> 269.09438 | I3: =IS!I10 -> 304.22614 | L3: Cash flows from investing activities
A4: NOPAT (Net Operating Profit After Tax) | B4: =B2-B3 -> 189.7 | C4: =C2-C3 -> 628.7 | D4: =D2-D3 -> 727.7 | E4: =E2-E3 -> 474.01662 | F4: =F2-F3 -> 566.52168 | G4: =G2-G3 -> 664.82986 | H4: =H2-H3 -> 765.88399 | I4: =I2-I3 -> 865.8744 | L4: Payments for property, plant and equipment | M4: -34.5 | N4: -10.6 | O4: -3.6
A5: Add back: D&A | B5: 20 | C5: 28.2 | D5: 32.9 | E5: =IS!E2*2% -> 38.822 | F5: =IS!F2*2% -> 45.03352 | G5: =IS!G2*2% -> 51.338213 | H5: =IS!H2*2% -> 57.498798 | I5: =IS!I2*2% -> 63.248678 | L5: Payments for intangible assets | M5: -0.9 | N5: -2.4 | O5: -5.2
A6: Less: Capex | B6: =O4+O5 -> -8.8 | C6: =N4+N5 -> -13 | D6: =M4+M5 -> -35.4 | E6: =E2*2% -> 12.81126 | F6: =F2*2% -> 15.311397 | G6: =G2*2% -> 17.968374 | H6: =H2*2% -> 20.699567 | I6: =I2*2% -> 23.402011 | L6: Payments for financial assets at FVOCI | M6: -6455.6 | N6: -9552.3 | O6: -8655.9
A7: Less: Change in Working Capital | B7: 7.9 | C7: 8.2 | D7: 3.7 | E7: =E2*0.5% -> 3.202815 | F7: =F2*0.5% -> 3.8278492 | G7: =G2*0.5% -> 4.4920936 | H7: =H2*0.5% -> 5.1748919 | I7: =I2*0.5% -> 5.8505027 | L7: Proceeds from sale and maturity of financial assets at FVOCI | M7: 5892.6 | N7: 9422.6 | O7: 6077.2
A8: Free Cash Flow to Firm (FCFF) | B8: =B4+B5-B6-B7 -> 210.6 | C8: =C4-C5-C6-C7 -> 605.3 | D8: =D4-D5-D6-D7 -> 726.5 | E8: =E4+E5-E6-E7 -> 496.82455 | F8: =F4+F5-F6-F7 -> 592.41596 | G8: =G4+G5-G6-G7 -> 693.7076 | H8: =H4+H5-H6-H7 -> 797.50833 | I8: =I4+I5-I6-I7 -> 899.87057 | L8: Proceeds from sublease | M8: – | N8: 0.1 | O8: 0.2
L9: Net cash used in investing activities | M9: -598.4 | N9: -142.6 | O9: -2587.3

Sheet DCF
A1: Year | B1: FY2026E | C1: FY2027E | D1: FY2028E | E1: FY2029E | F1: FY2030E
A2: FCFF | B2: =CF!E8 -> 496.82455 | C2: =CF!F8 -> 592.41596 | D2: =CF!G8 -> 693.7076 | E2: =CF!H8 -> 797.50833 | F2: =CF!I8 -> 899.87057
A3: Disount Factor | B3: =1/(1+Assumptions!$B$16)^1 -> 0.9218778 | C3: =1/(1+Assumptions!$B$16)^2 -> 0.84985869 | D3: =1/(1+Assumptions!$B$16)^3 -> 0.78346586 | E3: =1/(1+Assumptions!$B$16)^4 -> 0.72225979 | F3: =1/(1+Assumptions!$B$16)^5 -> 0.66583527
A4: PV of FCFF | B4: =B2*B3 -> 458.01152 | C4: =C2*C3 -> 503.46985 | D4: =D2*D3 -> 543.49622 | E4: =E2*E3 -> 576.0082 | F4: =F2*F3 -> 599.16556
A5: Sum of PV of FCFF | B5: =SUM(B4:F4) -> 2680.1513
A7: Terminal Value
A8: Terminal Value (Perpetuity) | B8: =F2*(1+Assumptions!B17)/(Assumptions!B16-Assumptions!B17) -> 16931.403
A9: PV of Terminal Value | B9: =B8/(1+Assumptions!B16)^5 -> 11273.525
A11: Terminal Value (Exit multiple) | B11: =IS!I7*18 -> 21061.81
A12: PV of Terminal Value | B12: =B11/(1+Assumptions!B16)^5 -> 14023.696
A14: Enterprise Value (Perpertuity Method) | B14: =B5+B9 -> 13953.676
A15: Less: Corporate Debt | B15: =98.1+1.3 -> 99.4
A16: Add: Corporate Cash | B16: =-(13982-17578) -> 3596
A17: Equity Value | B17: =B14-B15+B16 -> 17450.276
A18: Shares Outstanding | B18: 1040 | C18: Million Shares
A19: Implied Share price | B19: =B17/B18 -> 16.779112
A20: Current share price | B20: 10.87
A21: Variation | B21: =((B19-B20)/B20) -> 0.54361656

Sheet Sensitivity
B1: WACC vs Terminal Growth Rate | J1: WACC vs Exit Multiple
B2: =DCF!B19 -> 16.779112 | C2: 0.015 | D2: 0.02 | E2: 0.025 | F2: 0.03 | G2: 0.035 | H2: 0.04 | J2: =(DCF!B5+IS!I7*J18/(1+J16)^5-DCF!B15+DCF!B16)/DCF!B18 -> 19.426146 | K2: 10 | L2: 13 | M2: 18 | N2: 22 | O2: 25 | P2: 30
B3: 0.065 | C3: 18.912905 | D3: 20.407542 | E3: 22.275839 | F3: 24.677934 | G3: 27.880728 | H3: 32.364639 | J3: 0.065 | K3: 14.151049 | L3: 16.614609 | M3: 20.720541 | N3: 24.005287 | O3: 26.468847 | P3: 30.574779
B4: 0.07 | C4: 17.437493 | D4: 18.63768 | E4: 20.104575 | F4: 21.938194 | G4: 24.295704 | H4: 27.439051 | J4: 0.07 | K4: 13.960968 | L4: 16.367503 | M4: 20.378395 | N4: 23.587108 | O4: 25.993644 | P4: 30.004535
B5: 0.075 | C5: 16.209013 | D5: 17.190691 | E5: 18.368704 | F5: 19.808498 | G5: 21.60824 | H5: 23.922195 | J5: 0.075 | K5: 13.776142 | L5: 16.127229 | M5: 20.045708 | N5: 23.180492 | O5: 25.531579 | P5: 29.450058
B6: 0.08 | C6: 15.170458 | D6: 15.985833 | E6: 16.949457 | F6: 18.105806 | G6: 19.519122 | H6: 21.285766 | J6: 0.08 | K6: 13.596403 | L6: 15.893569 | M6: 19.722178 | N6: 22.785066 | O6: 25.082231 | P6: 28.910841
B7: 0.085 | C7: 14.28111 | D7: 14.967208 | E7: 15.767656 | F7: 16.71364 | G7: 17.848821 | H7: 19.236264 | J7: 0.085 | K7: 13.421588 | L7: 15.666309 | M7: 19.407511 | N7: 22.400473 | O7: 24.645194 | P7: 28.386396
B8: 0.09 | C8: 13.511107 | D8: 14.09489 | E8: 14.768486 | F8: 15.554348 | G8: 16.483093 | H8: 17.597588 | J8: 0.09 | K8: 13.25154 | L8: 15.445247 | M8: 19.101426 | N8: 22.026368 | O8: 24.220075 | P8: 27.876253
B9: 0.095 | C9: 12.838057 | D9: 13.339601 | E9: 13.912794 | F9: 14.574171 | G9: 15.345777 | H9: 16.257675 | J9: 0.095 | K9: 13.086109 | L9: 15.230187 | M9: 18.80365 | N9: 21.66242 | O9: 23.806497 | P9: 27.37996
B10: 0.1 | C10: 12.244834 | D10: 12.679381 | E10: 13.171868 | F10: 13.734711 | G10: 14.384144 | H10: 15.141816 | J10: 0.1 | K10: 12.925149 | L10: 15.020939 | M10: 18.513921 | N10: 21.308307 | O10: 23.404097 | P10: 26.89708
B16: 0.084742463 | J16: 0.0847
B17: 0.03
J18: 18

Sheet Comps
A1: Company | B1: EV/Ebitda | C1: EV/Revenue | D1: P/E
A2: Wise | B2: 17 | C2: 7.5 | D2: 27.4
A3: Paypal | B3: 5.01 | C3: 1.11 | D3: 7.97
A4: Adyen | B4: 10.9 | C4: 6.38 | D4: 25.47
A5: Remitly | B5: 20.67 | C5: 2.04 | D5: 40.92
A7: Mean | B7: =AVERAGE(B2:B5) -> 13.395 | C7: =AVERAGE(C2:C5) -> 4.2575 | D7: =AVERAGE(D2:D5) -> 25.44
A8: Median | B8: =MEDIAN(B2:B5) -> 13.95 | C8: =MEDIAN(C2:C5) -> 4.21 | D8: =MEDIAN(D2:D5) -> 26.435
